quri_parts/rust/__init__.py
quri_parts/rust/py.typed
quri_parts/rust/quri_parts_rust.pyd
quri_parts/rust/circuit/__init__.py
quri_parts/rust/circuit/circuit.pyi
quri_parts/rust/circuit/circuit_parametric.pyi
quri_parts/rust/circuit/gate.pyi
quri_parts/rust/circuit/gates.pyi
quri_parts/rust/circuit/noise.pyi
quri_parts/rust/circuit/parameter.pyi
quri_parts/rust/qulacs/__init__.py
quri_parts/rust/qulacs/__init__.pyi
quri_parts_rust-0.24.1.dist-info/licenses/NOTICE
quri_parts_rust-0.24.1.dist-info/METADATA
quri_parts_rust-0.24.1.dist-info/WHEEL
quri_parts_rust-0.24.1.dist-info/top_level.txt
quri_parts_rust-0.24.1.dist-info/RECORD
