Metadata-Version: 2.4
Name: quri-parts-rust
Version: 0.24.1
Summary: Platform-independent quantum circuit library
Author-email: QURI Parts Authors <opensource@qunasys.com>
License: Apache-2.0
Project-URL: Repository, https://github.com/QunaSys/quri-sdk
Project-URL: Documentation, https://quri-parts.qunasys.com
Keywords: quantum,quantum computing
Classifier: Topic :: Scientific/Engineering :: Physics
Classifier: Typing :: Typed
Requires-Python: <4.0.0,>=3.9.8
License-File: NOTICE
Requires-Dist: typing-extensions<5.0.0,>=4.1.1
Requires-Dist: numpy>=1.22.0
Dynamic: license-file
